graphbook_huggingface/__init__.py
graphbook_huggingface/dist/bundle.js
graphbook_huggingface/dist/bundle.js.LICENSE.txt
graphbook_huggingface/hf_datasets.py
graphbook_huggingface/hf_pipeline.py
graphbook_huggingface/hf_postprocessing.py
graphbook_huggingface-0.0.6.dist-info/LICENSE
graphbook_huggingface-0.0.6.dist-info/METADATA
graphbook_huggingface-0.0.6.dist-info/WHEEL
graphbook_huggingface-0.0.6.dist-info/RECORD
