Metadata-Version: 2.3
Name: graphbook_huggingface
Version: 0.0.6
Summary: Graphbook Hugging Face Plugin for no-code Hugging Face AI pipelines
License: MIT
Keywords: huggingface,ml,workflow,pipelines,pytorch,data science,machine learning,ai
Author: Richard Franklin
Author-email: rsamf@graphbook.ai
Requires-Python: >=3.9,<4.0
Classifier: License :: OSI Approved :: MIT License
Classifier: Operating System :: OS Independent
Classifier: Programming Language :: Python :: 3
Classifier: Programming Language :: Python :: 3.9
Classifier: Programming Language :: Python :: 3.10
Classifier: Programming Language :: Python :: 3.11
Classifier: Programming Language :: Python :: 3.12
Classifier: Programming Language :: Python :: 3.13
Project-URL: Documentation, https://docs.graphbook.ai
Project-URL: Homepage, https://graphbook.ai
Project-URL: Repository, https://github.com/graphbookai/graphbook
